catchery/__init__.py
catchery/error_handler.py
catchery/validation.py
catchery-0.6.5.dist-info/licenses/LICENSE.md
catchery-0.6.5.dist-info/METADATA
catchery-0.6.5.dist-info/WHEEL
catchery-0.6.5.dist-info/top_level.txt
catchery-0.6.5.dist-info/RECORD
