Metadata-Version: 2.4
Name: catchery
Version: 0.6.5
Summary: A python error handler. Catch exceptions and handle them gracefully.
Author-email: Enrico Fraccaroli <enrico.fraccaroli@univr.it>
Maintainer-email: Enrico Fraccaroli <enrico.fraccaroli@univr.it>
License-Expression: MIT
Project-URL: Homepage, https://github.com/Galfurian/catchery
Project-URL: Repository, https://github.com/Galfurian/catchery
Project-URL: Bug Tracker, https://github.com/Galfurian/catchery/issues
Keywords: error-handling,exceptions,python
Requires-Python: >=3.11
License-File: LICENSE.md
Dynamic: license-file
